PKG-INFO
pyproject.toml
giaocr/__init__.py
giaocr/__version__.py
giaocr/PPOCRModels/LICENSE
giaocr/PPOCRModels/README.md
giaocr/PPOCRModels/en_US/det/inference.onnx
giaocr/PPOCRModels/en_US/det/version.txt
giaocr/PPOCRModels/en_US/pddet/inference.pdiparams
giaocr/PPOCRModels/en_US/pddet/inference.pdiparams.info
giaocr/PPOCRModels/en_US/pddet/inference.pdmodel
giaocr/PPOCRModels/en_US/pdrec/inference.pdiparams
giaocr/PPOCRModels/en_US/pdrec/inference.pdiparams.info
giaocr/PPOCRModels/en_US/pdrec/inference.pdmodel
giaocr/PPOCRModels/en_US/rec/inference.onnx
giaocr/PPOCRModels/en_US/rec/keys.txt
giaocr/PPOCRModels/en_US/rec/version.txt
giaocr/PPOCRModels/zh_CN/det/inference.onnx
giaocr/PPOCRModels/zh_CN/det/version.txt
giaocr/PPOCRModels/zh_CN/pddet/inference.pdiparams
giaocr/PPOCRModels/zh_CN/pddet/inference.pdiparams.info
giaocr/PPOCRModels/zh_CN/pddet/inference.pdmodel
giaocr/PPOCRModels/zh_CN/pdrec/inference.pdiparams
giaocr/PPOCRModels/zh_CN/pdrec/inference.pdiparams.info
giaocr/PPOCRModels/zh_CN/pdrec/inference.pdmodel
giaocr/PPOCRModels/zh_CN/rec/inference.onnx
giaocr/PPOCRModels/zh_CN/rec/keys.txt
giaocr/PPOCRModels/zh_CN/rec/version.txt
giaocr-0.0.2.dist-info/METADATA
giaocr-0.0.2.dist-info/WHEEL
giaocr-0.0.2.dist-info/RECORD
